{"1":[[22,0]],"2":[[27,16],[35,0]],"6":[[29,7]],"9":[[24,0]],"_0":"Adolfo Alsina","a":[[0,0],[0,7],[1,0],[11,10],[13,0],[20,0],[21,14],[25,0],[26,0],[29,12],[32,7],[35,5],[44,16],[45,5]],"_1":"Avenida Perón","p":[[1,8],[10,4],[13,8],[27,5],[28,8],[29,0],[31,0],[33,14],[36,10],[41,0],[41,11]],"_2":"Montevideo","m":[[2,0],[11,0],[12,0],[14,0],[15,0],[15,8],[17,4],[18,0],[26,7],[28,0],[30,6],[31,10],[37,5],[38,10],[42,0],[43,0],[44,9],[45,9]],"_3":"Juan B. Riolfo","j":[[3,0],[21,0],[24,5],[33,0]],"b":[[3,5],[5,0],[13,14],[14,7],[32,0],[34,7],[36,16],[38,0],[46,5],[46,13]],"r":[[3,8],[5,11],[19,0],[27,0],[39,0]],"_4":"Estanislao Zeballos","e":[[4,0],[6,0],[10,0]],"z":[[4,11]],"_5":"Bernardino Rivadavia","_6":"España","_7":"Independencia","i":[[7,0],[30,0]],"_8":"Héctor Vendramini","h":[[8,0]],"v":[[8,7],[40,8]],"_9":"Libertad","l":[[9,0],[23,0],[42,7],[45,15]],"_10":"Eva Peron","_11":"Marcelino Amor","_12":"Marilú","_13":"Avenida Padre Buodo","_14":"Manuel Belgrano","_15":"Mariano Moreno","_16":"Domingo Faustino Sarmiento","d":[[16,0],[22,3],[24,2],[29,9],[33,6],[34,0],[35,2],[44,0],[45,0],[46,0]],"f":[[16,8]],"s":[[16,17],[17,0]],"_17":"San Martín","_18":"Maipú","_19":"Rondeau","_20":"Alejo Griot","g":[[20,6],[21,5]],"_21":"José Gervasio Artigas","_22":"12 de Octubre","o":[[22,6]],"_23":"Lavallejas","_24":"9 de Julio","_25":"Ayacucho","_26":"Adolfo Mengelle","_27":"Ruta Provincial 28","_28":"Maestro Pradier","_29":"Pasaje 6 de Abril","_30":"Islas Malvinas","_31":"Pasaje Y. Miguel","y":[[31,7]],"_32":"Buenos Aires","_33":"Jorge Delfino Pardou","_34":"Daniel Bonjour","_35":"2 de Abril","_36":"Colectora Padre Buodo","c":[[36,0],[40,0],[44,22]],"_37":"Nena Maina","n":[[37,0]],"_38":"Bartolomé Mitre","_39":"Rivera","_40":"Colonos Valdenses","_41":"Presidente Peron","_42":"Martin Lutero","_43":"Moreno","_44":"Diputado Miguel Angel Cicare","_45":"Dra. Ana Maria Lazaric","_46":"Dra. Beatriz Barrancos","#prov_name":"La Pampa","#city_name":"Jacinto Aráuz"}