{"2":[21,33],"9":[28],"_0":"Carlos Gardel","c":[0,11,15,23,26],"g":[0],"_1":"Nicolás Avellaneda","n":[1],"a":[1,17,19,22,23],"_2":"Belgrano","b":[2,12,27],"_3":"San Martín","s":[3,5,9,10],"m":[3,4,7,8,12,14,21,29],"_4":"Daniel Morra","d":[4,11,18,21,24,25,26,28],"_5":"Roque Saenz Peña","r":[5,6,20,32,33],"p":[5,8,15,22,30,33],"_6":"Rivadavia","_7":"Mariano Moreno","_8":"José María Paz","j":[8,11,25,26,28],"_9":"Sarmiento","_10":"Vélez Sarsfield","v":[10,13],"_11":"Jerónimo Luis de Cabrera","l":[11,13,31],"_12":"Bartolomé Mitre","_13":"Vicente López","_14":"Mansilla","_15":"Carlos Pellegrini","_16":"Tarditti","t":[16],"_17":"Almafuerte","_18":"Derqui","_19":"Ameghino","_20":"Ricardo Rojas","_21":"25 de Mayo","_22":"Patricias Argentinas","_23":"Arturo Capdevila","_24":"Deán Funes","f":[24],"_25":"Justo J. de Urquiza","u":[25],"_26":"Juan del Campillo","_27":"Bulnes","_28":"9 de Julio","_29":"Manuel Estrada","e":[29],"_30":"Perón","_31":"Leopoldo Lugones","_32":"Roma","_33":"Ruta Provincial 27"}