{"0":[0,14],"1":[8],"2":[12,17],"9":[13],"_0":"Camino Secundario 011-08","C":[0,14,18],"S":[0,4,5,14,20],"_1":"Patricias Argentinas","P":[1,7,24],"A":[1,10,15],"_2":"John Kennedy","J":[2,13,17],"K":[2],"_3":"Mariano Moreno","M":[3,4,7,11,12,16,21,22,24],"_4":"San Martín","_5":"Sarmiento","_6":"Belgrano","B":[6,10,11,19],"_7":"Perito Moreno","_8":"12 de Octubre","d":[8,12,13,17],"O":[8],"_9":"Laprida","L":[9],"_10":"Avenida Bolívar","_11":"Bartolomé Mitre","_12":"25 de Mayo","_13":"9 de Julio","_14":"Camino Secundario 011-01","_15":"Antártida Argentina","_16":"Islas Malvinas","I":[16],"_17":"20 de Junio","_18":"Camino Del Valle - Hale","D":[18],"V":[18],"-":[18],"H":[18],"_19":"B Rivadavia","R":[19],"_20":"Sn","_21":"Mbelgrano","_22":"Mmoreno","_23":"Nlaprida","N":[23],"_24":"Perito Morteno"}