{"1":[[27,0]],"7":[[28,16]],"_0":"Leandro N. Alem","l":[[0,0],[9,0]],"n":[[0,8],[13,4],[29,14],[30,9],[31,7],[32,6],[33,21],[34,10],[35,11]],"a":[[0,11],[1,0],[3,7],[11,6],[26,0],[29,6]],"_1":"Avenida Juan Bautista Gil","j":[[1,8],[11,0],[29,0]],"b":[[1,13],[3,0],[5,0],[10,0],[12,0],[20,0],[33,0]],"g":[[1,22]],"_2":"Pavón","p":[[2,0],[9,3],[17,4],[24,7],[25,0],[28,5],[32,0]],"_3":"Buenos Aires","_4":"Sarmiento","s":[[4,0],[7,0],[13,0],[17,0],[19,0],[34,0]],"_5":"Bernardo de Irigoyen","d":[[5,9],[16,0],[27,3],[31,0],[33,9]],"i":[[5,12],[22,0],[33,12]],"_6":"Rincón","r":[[6,0],[11,9],[28,0],[29,9]],"_7":"San Martín","m":[[7,4],[8,0],[18,0],[21,0],[22,6],[35,0]],"_8":"Moreno","_9":"La Plata","_10":"Belgrano","_11":"Julio A. Roca","_12":"Bella Vista","v":[[12,6],[23,0],[30,0]],"_13":"San Nicolás","_14":"Tres Esquinas","t":[[14,0]],"e":[[14,5],[27,6]],"_15":"Chile","c":[[15,0],[24,0],[26,8]],"_16":"Donado","_17":"San Pedro","_18":"Mitre","_19":"Sauce","_20":"Brasil","_21":"Montevideo","_22":"Islas Malvinas","_23":"Victoria","_24":"Cuatro Picos","_25":"Pellegrini","_26":"Avenida Corrales","_27":"12 de Enero","_28":"Ruta Provincial 72","_29":"Julio A. Roca norte","_30":"Victoria norte","_31":"Donado norte","_32":"Pavón norte","_33":"Bernardo de Irigoyen norte","_34":"Sarmiento norte","_35":"Montevideo norte","#prov_name":"Buenos Aires","#city_name":"Saldungaray"}