{"2":[35],"_0":"Francisco Casis","f":[0,28],"c":[0,3,4,8,15,25,26,27,32],"_1":"Atahualpa Yupanqui","a":[1,2,4,5,6,7,8,12,17,18,26,31,32],"y":[1],"_2":"Alfredo Zitarrosa","z":[2,18,19],"_3":"Carlos Santamaría","s":[3,11,29],"_4":"Avenida Carlos Gardel","g":[4,28],"_5":"Isaco Abitbol","i":[5],"_6":"Abelardo Dimotta","d":[6,30],"_7":"Aníbal Troilo","t":[7,13,21],"_8":"Avenida Linares Cardozo","l":[8,20,24,31],"_9":"Mario Millán Medina","m":[9,10,11,16,23],"_10":"Julio Migno","j":[10,13,16,24,26,27,30,32],"_11":"Mercedes Sosa","_12":"Ariel Ramirez","r":[12,15,19,21,35],"_13":"Jaime Torres","_14":"Edmundo Pérez","e":[14,22,23],"p":[14,22,35],"_15":"Chango Rodríguez","_16":"Jorge Mendez","_17":"Hermanos Abalos","h":[17,25,33],"_18":"Anibal Zampayo","_19":"Ricardo Zandomeni","_20":"Luis Landriscina","_21":"Tarragó Ros","_22":"E. Pignocco","_23":"Ernesto Montiel","_24":"Julio Luján","_25":"Hermanos Cuestas","_26":"Juan C. Angelino","_27":"Jorge Cafrune","_28":"Federico Gutierrez","_29":"Santiago Satler","_30":"Jaime Dávalos","_31":"Avenida Lucrecia Odiard","o":[31],"_32":"Juan Carlos Alsina","_33":"Hermanos Benítez","b":[33],"_34":"Víctor Velázquez","v":[34],"_35":"Ruta Provincial 23"}