{"1":[0],"_0":"Ruta Provincial 10","r":[0],"p":[0,1,4,10,11,21,22],"_1":"Pedro Ignacio Guzmán","i":[1],"g":[1,8],"_2":"Capitán Francisco Domingo Zarco","c":[2,7,8,10,13,14,16,19,20,21,23],"f":[2,3,4,5,10,13,14,23],"d":[2,5,6,7,15,17,21,23],"z":[2,16,18],"_3":"Monseñor Juan Bautista Fassi","m":[3,6,8,9,12,15,21],"j":[3,7,9],"b":[3,14,17,18,20,23],"_4":"Fray Quirino Porreca","q":[4],"_5":"Fray Francisco Davila","_6":"Marqués de Sobremonte","s":[6],"_7":"Avenida Jerónimo Luis de Cabrera","a":[7,11,16,19],"l":[7,15],"_8":"Cacique Gabriel Mutupillo","_9":"Juan Montenegro","_10":"Padre Fermin Calatayud","_11":"Obispo Pedro Argandona","o":[11,18,22],"_12":"Elías Moyano","e":[12],"_13":"Fray Cayetano Fernández","_14":"Capitán Francisco Baigorri","_15":"Manuel de la Lastra","_16":"Capitán Alejo Zalazar","_17":"Hernando de Torre Blanca","h":[17],"t":[17],"_18":"Obispo Zenón Bustos","_19":"Arzobispo Castellanos","_20":"Cacique Bravo","_21":"Pasaje Doctor Mateo Carusillo","_22":"Pedro Ordoñez","_23":"Cap Francisco Del Barco"}