{"1":[37,101],"2":[5,51,76],"9":[8],"_0":"Avenida Las Chacras","a":[0,1,3,7,9,10,11,12,13,14,19,20,30,35,38,39,41,42,54,63,71,83,85,93,97,100,102,103,109,113,114,121,142,158,159,160,161,164,165,174,178],"l":[0,1,6,13,15,16,18,19,23,25,28,32,44,45,46,47,48,52,55,57,58,59,60,66,67,68,69,71,77,78,79,81,83,84,86,88,90,91,94,97,105,107,109,110,113,114,115,118,121,122,124,128,129,131,132,136,137,138,139,141,142,143,147,148,152,155,156,158,162,166,174,178],"c":[0,11,12,14,16,18,19,21,26,28,32,36,40,49,55,63,71,72,77,78,84,89,90,96,108,111,122,138,145,146,149,168,171,178,179],"_1":"Autopista Los Puquios","p":[1,6,7,8,10,12,15,24,25,27,30,50,52,53,74,75,87,95,102,113,126,130,135,140,143,145,150,155,159,160,164,167,171,176,177,181],"_2":"Fátima","f":[2,51,65,101,119,127,151,161,169],"_3":"Ejército Argentino","e":[3,13,23,80,88,108,115,116,119,126,135,140,144,173],"_4":"Huarpes","h":[4,15,21,25,57,83,86,99,139,157,175,177],"_5":"20 de Noviembre","d":[5,7,10,11,12,16,18,24,28,32,37,39,40,51,52,59,62,72,74,76,78,101,109,113,160,161,169,171,173],"n":[5,19,39,92],"_6":"Los Pejes","_7":"Avenida Teniente Juan D. Perón","t":[7,46,66,73,104,105,109,147],"j":[7,55,62,65,67,73,75,76,80,92,100,112,116,125,144,156,159,162,163],"_8":"Ruta Provincial 9","r":[8,9,22,28,31,33,45,52,56,61,64,70,78,100,102,118,124,128,129,169,175],"_9":"Avenida San Roque","s":[9,17,24,27,33,40,49,54,61,62,67,70,74,81,112,125,130,131,134,135,148,151,157,159,163,168,170,176,180],"_10":"Aguada de Pueyrredón","_11":"Avenida del Viento Chorrillero","v":[11,72,73,98,117,166,179,181],"_12":"Avenida Cruz de Piedra","_13":"Avenida Los Eucaliptos","_14":"Avenida Cuchi Corral","_15":"La Pancha Hernández","_16":"Cerro de la Cruz","_17":"Sosa","_18":"Cristo de la Quebrada","q":[18,44,106,107,110,137],"_19":"Avenida Central Los Nogales","_20":"Agüero","_21":"Cañada Honda","_22":"Renca","_23":"Los Espinillos","_24":"Puesta del Sol","_25":"Pasaje Los Hornos","_26":"Comechingones","_27":"Soldados Puntanos","_28":"Río de las Carpas","_29":"Isleño","i":[29,75],"_30":"Alto Pencoso","_31":"Roger Balet","b":[31,47,53,73,93,106,116,120,133,173],"_32":"Campamento de las Chacras","_33":"Río Salado","_34":"Montiel","m":[34,37,38,43,50,52,58,64,68,80,87,91,94,119,123,132,134,141,150,170,172,173,174],"_35":"América","_36":"Conlara","_37":"1 de Mayo","_38":"Malvinas Argentinas","_39":"Niñas de Ayohuma","_40":"Sauces del Chorrillo","_41":"Anchorena","_42":"Artesanos Koslayenses","k":[42,96],"_43":"Manantial","_44":"Los Quebrachos","_45":"Los Ranqueles","_46":"Los Tintitacos","_47":"Las Brisas","_48":"Los Ligustros","_49":"Costanera Sur","_50":"Maestros Puntanos","_51":"28 de Febrero","_52":"María Reina de la Paz","_53":"Pasaje Berardi","_54":"Alfonsina Storni","_55":"Juan Crisóstomo Lafinur","_56":"Regino Garro","g":[56,65,82,107,127,154,159],"_57":"Las Higueras","_58":"Los Membrillos","_59":"Los Duraznos","_60":"Los Liquidambares","_61":"Río Socoscora","_62":"Doctor Juan Saá","_63":"Chocho Arancibia","_64":"Miguel Roca","_65":"Juan Gilberto Funes","_66":"Los Talas","_67":"Juan Sánchez Lafuente","_68":"Las Moras","_69":"Las Lambertianas","_70":"San Roque","_71":"Avenida Los Castaños","_72":"Virgen del Carmen","_73":"Boulevard José Toribio Videla","_74":"Pasaje Santo Domingo","_75":"Juan Pablo II","_76":"26 de Julio","_77":"La Carolina","_78":"R. de las Carpas","_79":"Los Olmos","o":[79,112,130,153,159],"_80":"José Manuel Estrada","_81":"Los Socavones","_82":"González","_83":"Avenida Las Hiedras","_84":"Las Casuarinas","_85":"Alameda","_86":"Las Hortensias","_87":"Puerto Madryn","_88":"La Escondida","_89":"Chipiscú","_90":"Los Cipreses","_91":"Los Molles","_92":"Urbano Joaquín Núñez","u":[92,170],"_93":"Boulevard Anglada","_94":"Las Madreselvas","_95":"Pancato","_96":"Cacique Koslay","_97":"Los Abetos","_98":"Vicente Vázquez","_99":"Hornos","_100":"Arturo Rodriguez Jurado","_101":"18 de Febrero","_102":"Pasaje Alfonso Rodríguez","_103":"Araucanos","_104":"Tomolasta","_105":"Las Tipas","_106":"Quebracho Blanco","_107":"Gobernador Lindor Quiroga","_108":"El Caldén","_109":"Teresa de los Andes","_110":"La Quinta","_111":"Concarán","_112":"San José Obrero","_113":"Aguada de los Padres","_114":"Los Alerces","_115":"Los Elliotis","_116":"Escribano Jorge Bertín","_117":"Velazco","_118":"Los Retamos","_119":"Fray Mamerto Esquiú","_120":"Basilio Bustos","_121":"Las Artes","_122":"Los Cerros","_123":"Mendoza","_124":"Los Robles","_125":"San Juan","_126":"El Pino","_127":"Gregorio Franco","_128":"Las Rosas","_129":"La Rioja","_130":"Paulino Sosa Oeste","_131":"San Lorenzo","_132":"La Marqueza","_133":"Benteveo","_134":"San Miguel","_135":"Paulino Sosa Este","_136":"Los Leños","_137":"Las Quijadas","_138":"La Calandria","_139":"Los Horneros","_140":"Paraíso Escondido","_141":"Los Manzanos","_142":"Las Acacias","_143":"Los Paraísos","_144":"El Jilguero","_145":"Contribución Patriótica","_146":"Carpintero","_147":"Las Torcazas","_148":"San Luis","_149":"Cardenal","_150":"Martín Pescador","_151":"Santa Fe","_152":"Los Zorzales","z":[152],"_153":"Osorio","_154":"Guerrero","_155":"Los Picahuesos","_156":"Januario Luna","_157":"Huarpes Sur","_158":"Los Aromos","_159":"Avenida Parque Gobernador José Santos Ortiz","_160":"Avenida del Portezuelo","_161":"Avenida del Fundador","_162":"La Joaquina","_163":"San José","_164":"Pampa Azul","_165":"Atahualpa Yupanqui","y":[165,181],"_166":"Lorenzo Vargas","_167":"Puntanito","_168":"San Cayetano","_169":"Doctor René Favaloro","_170":"Miguel U. Suárez","_171":"Perilago Cruz de Piedra","_172":"Michilingües","_173":"María E. de Berruetta","_174":"Avenida Las Magnolias","_175":"Rosendo Hernández","_176":"Paulino Sosa","_177":"Humberto Primo","_178":"Avenida Los Crespones","_179":"Camino Verde","_180":"Salida","_181":"Propietarios y visitas"}