{"_0":"Benito Juárez","b":[[0,0],[1,21],[2,0],[3,4],[5,12],[6,0],[19,0],[21,0],[22,17],[27,6],[34,0],[37,15],[41,0],[51,11],[61,13],[65,0],[74,13]],"j":[[0,7],[11,7],[13,0],[37,7],[61,8],[61,22],[74,8]],"_1":"Pedro Calderón de la Barca","p":[[1,0],[35,0],[35,6],[37,0],[38,0],[39,20],[56,11],[66,0],[66,7],[69,7],[76,0]],"c":[[1,6],[14,0],[15,0],[17,9],[23,16],[26,0],[27,0],[29,8],[42,0],[42,7],[47,8],[50,7],[51,0],[55,11],[63,20],[64,0],[67,0],[71,0],[76,4]],"d":[[1,15],[4,9],[4,21],[5,0],[11,0],[12,6],[22,0],[23,9],[29,14],[36,0],[39,14],[49,8],[52,15],[55,8]],"l":[[1,18],[5,7],[14,14],[23,12],[25,0],[28,0],[39,17],[52,6],[58,0],[75,0]],"_2":"Bermúdez","_3":"San Blas","s":[[3,0],[4,24],[10,0],[23,0],[24,3],[28,3]],"_4":"Remedios de Escalada de San Martín","r":[[4,0],[14,8],[16,0],[33,8],[40,0],[52,18],[55,0],[59,0]],"e":[[4,12],[24,0],[49,0],[50,0],[52,0],[53,0]],"m":[[4,28],[8,0],[17,0],[31,0],[39,0],[56,0],[60,7],[62,0],[63,10],[68,0],[69,0],[70,0],[73,0]],"_5":"Doctor Luis Beláustegui","_6":"Bernaldes","_7":"Atahualpa","a":[[7,0],[9,6],[11,19],[32,0],[33,0],[37,12],[39,6],[47,0],[48,0],[57,0],[61,0],[63,0],[74,0],[74,22]],"_8":"Moctezuma","_9":"Tupac Amaru","t":[[9,0],[38,7]],"_10":"Sarachaga","_11":"Doctor Juan Felipe Aranguren","f":[[11,12],[12,9],[13,5],[14,22],[20,0],[30,17],[39,26],[53,3]],"_12":"Gómez de Fonseca","g":[[12,0],[18,0],[29,0],[30,0],[45,0],[48,8],[59,4]],"_13":"Juan Francisco Olmos","o":[[13,15],[22,9],[46,0],[57,8]],"_14":"Coronel Ramón Lorenzo Falcón","_15":"Cardoso","_16":"Rafaela","_17":"Martínez Castro","_18":"Goya","_19":"Belén","_20":"Fernández","_21":"Bolaños","_22":"Diputado Osvaldo Benedetti","_23":"Santiago de las Carreras","_24":"El Sereno","_25":"Lobería","_26":"Checoslovaquia","_27":"César Bacle","_28":"La Selva","_29":"General César Díaz","_30":"General Venancio Flores","v":[[30,8],[60,0]],"_31":"Mercedes","_32":"Avellaneda","_33":"Avenida Rivadavia","_34":"Bogotá","_35":"Pablo Podestá","_36":"Delambre","_37":"Pasaje Juan A. Boeri","_38":"Pasaje Trieste","_39":"María Antonia de la Paz y Figueroa","y":[[39,24],[56,9],[72,0]],"_40":"Rubens","_41":"Beyrouth","_42":"Carlos Carranza","_43":"Hungría","h":[[43,0],[54,0]],"_44":"Wagner","w":[[44,0]],"_45":"Gualeguaychú","_46":"Olivieri","_47":"Avenida Carrasco","_48":"Avenida Gaona","_49":"Edmundo Damicis","_50":"Emilio Castelar","_51":"Conscripto Bernardi","_52":"Elena Larroque de Roffo","_53":"El Fuerte","_54":"Hinojo","_55":"Rosalia de Castro","_56":"Menéndez y Pelayo","_57":"Avenida Olivera","_58":"Lacarra","_59":"Río Grande","_60":"Virrey Melo","_61":"Avenida Juan Bautista Justo","_62":"Morón","_63":"Alejandro Magariños Cervantes","_64":"Cervantes","_65":"Bacacay","_66":"Pasaje Particular","_67":"Cajaravilla","_68":"Mozart","_69":"Marcos Paz","_70":"Murature","_71":"Camarones","_72":"Yerbal","_73":"Moreto","_74":"Avenida Juan Bautista Alberdi","_75":"Laguna","_76":"Pio Collivadino"}