{"1":[97],"2":[152],"3":[107],"9":[53],"_0":"Uspallata","u":[0,47,162],"_1":"Chile","c":[1,13,26,32,33,41,57,64,71,75,76,82,84,90,92,103,105,112,113,137,146,147,148,151,153,154,155,164,174,175,185,189],"_2":"Intendente Viotti","i":[2,17,24,68,75,87,95,108,127,130,151,157,158,176,185,201],"v":[2,28,39,66,70,124,176,199],"_3":"Pasaje Bolivar","p":[3,10,11,15,16,18,25,27,34,36,37,38,39,40,41,49,52,54,55,56,66,67,68,69,70,74,79,83,85,87,97,102,103,104,105,106,107,108,109,111,113,114,117,118,131,133,137,138,141,155,161,163,164,165,167,187,195],"b":[3,6,21,23,33,59,80,82,86,92,110,111,121,122,128,130,132,134,142,144,150,169,171,172],"_4":"Sarmiento","s":[4,8,11,27,28,31,38,40,44,50,57,68,69,72,76,77,79,83,88,91,94,103,113,118,122,135,136,139,161,169,173,182,185,187,193,194],"_5":"Lavalle","l":[5,7,12,17,29,36,45,51,63,70,73,74,79,82,94,99,109,116,117,125,148,153,159,165,173,187,192],"_6":"Buenos Aires","a":[6,10,17,19,23,30,35,43,54,61,65,73,85,98,101,112,126,127,135,139,141,147,149,150,151,163,168,177,183,184,190,192,198],"_7":"Las Heras","h":[7,131,157,163,175,178,179,189,200],"_8":"Suipacha","_9":"Entr Rios","e":[9,22,29,34,77,88,96,123,124,126,136,145,146,149,177,183,191,196,199],"r":[9,42,45,48,50,59,62,69,84,97,107,111,116,117,119,120,132,142,143,150,166,178,181,195,197],"_10":"Pasaje América","_11":"Pasaje San Jose","j":[11,14,25,36,44,52,53,68,79,81,84,85,111,118,122,125,127,137,140,143,144,166,175,179,184,190,197,200],"_12":"Doctor Francisco L. M. Lupi","d":[12,35,53,55,60,69,74,77,78,83,88,104,111,115,117,119,123,131,135,145,152,153,156,173,178,179,180,184,192,193,200],"f":[12,34,58,60,61,72,80,106,119,121,130,141,148,172,180,188,201],"m":[12,18,20,29,31,35,51,61,65,69,86,89,91,102,108,113,123,124,128,132,152,156,160,167,169,171,174,180,184,186,190],"_13":"Corrientes","_14":"Jose T. Taberna","t":[14,35,36,55,74,93,140,170,182,188,198],"_15":"General Paz","g":[15,42,48,108,126,129,132,135,153,167,168,169,181],"_16":"Pasteur","_17":"Avenida Los Inmigrantes","_18":"Pasaje Misiones","_19":"Avellaneda","_20":"Mariano Moreno","_21":"Bolivia","_22":"España","_23":"Almirante Brown","_24":"Independencia","_25":"Pasaje Juan Panero","_26":"Catamarca","_27":"Sáenz Peña","_28":"Vélez Sarsfield","_29":"Escribano Luis Morelli","_30":"Alberdi","_31":"San Martín","_32":"Chacabuco","_33":"Cura Brochero","_34":"Pasaje Enriqueta Funes","_35":"Marcelo T. de Alvear","_36":"Pasaje José T. Luque","_37":"Pasaje Neuquén","n":[37,47,55,73,92,100,104,115,138,173,191,192,194],"_38":"Pasaje Sosa","_39":"Pasaje Venesuela","_40":"Pasaje Simon Pignata","_41":"Pasaje Calzolari","_42":"General Roca","_43":"Ameghino","_44":"San Juan","_45":"La Rioja","_46":"Yapeyú","y":[46,70,186],"_47":"Naciones Unidas","_48":"Ricardo Gutiérrez","_49":"Paraguay","_50":"Santa Rosa","_51":"Medardo Álvarez Luque","á":[51,75],"_52":"Juan José Paso","_53":"9 de Julio","_54":"Antonio Palmero","_55":"Pasaje T de Nanoit","_56":"Parana","_57":"Sargento Cabral","_58":"Formosa","_59":"Bernardino Rivadavia","_60":"Deán Funes","_61":"Avenida Martin Fierro","_62":"Reconquista","_63":"Liniers","_64":"Chaco","_65":"Malvinas Argentinas","_66":"Pasaje Visconti","_67":"Pasaje Publico","_68":"Pasaje Intendente J. Sclaverano","_69":"Pasaje Senador Reyna de Maghini","_70":"Vicente López y Planes","_71":"Colon","_72":"Santa Fe","_73":"Leandro N. Alem","_74":"Pasaje D. T. Latella","_75":"Intendente Isidoro Calvo Álvarez","_76":"clemente soldado","_77":"Santiago del Estero","_78":"Defensa","_79":"Pasaje Soldado J. Ludueña","_80":"Francisco Bella","_81":"Jujuy","_82":"Bombero Luis Cuggino","_83":"Pasaje Santo Domingo","_84":"Ramón J. Carcano","_85":"Pasaje J. J. Arraras","_86":"Manuel Belgrano","_87":"Intendente Pardal","_88":"Edhit Sturm de Zanello","z":[88,110,133,168],"_89":"Maipu","_90":"Córdoba","_91":"Silvio Moncada","_92":"Beato Ceferino Namuncurá","_93":"Tucumán","_94":"San Lorenzo","_95":"Ituzaingó","_96":"Esquiu","_97":"Ruta Provincial 13","_98":"Alem","_99":"Laprida","_100":"Nacayal","_101":"Antartida Argentina","_102":"Pasaje Mexico","_103":"Pasaje Santa Cruz","_104":"Pasaje Divino Niño","_105":"Pasaje Chubut","_106":"Pasaje Falucho","_107":"Ruta Provincial 3","_108":"Pasaje Isla Gran Malvina","_109":"Pedro Ludueña","_110":"Balbino Zurbano","_111":"Pasaje Doctor Juan B. Roland","_112":"Avenida Centenario","_113":"Pasaje Suboficial Miguel Cardone","_114":"Pasaje Peru","_115":"Doctor Donato Nannini","_116":"Luis Raimondi","_117":"Profesor Lydia de Rozo","_118":"Juan S. Palmero","_119":"Doctor René Favaloro","_120":"Rolando Rubiolo","_121":"Francisco Beltrami","_122":"Senador José Basso","_123":"Enfermera Elena de Murúa","_124":"Enfermera María Verrúa","_125":"José Lenta","_126":"Elio A. Grosso","_127":"Avenida Intendente José Irazusta","_128":"Bartolomé Mitre","_129":"Güemes","_130":"Instructor Fernando Bossi","_131":"Profesor Hernán Durando","_132":"Gobernador Ramón B. Mestre","_133":"Pedro Zanello","_134":"Osvaldo Boeris","o":[134,196],"_135":"Gobernador Doctor Amadeo Sabattini","_136":"Esperanza Sanchez","_137":"Pastor José Crena","_138":"Presidente Nestor Kirchner","k":[138],"_139":"Abraham Salamanca","_140":"Julio Tristany","_141":"Presidente Arturo Frondizi","_142":"Bernardino Rueda","_143":"José Rópolo","_144":"Jorge Baravalle","_145":"Enfermera Dioniso Dugoni","_146":"Constructor Ernesto Chavez","_147":"Constructor Aldo Cantoni","_148":"Constructor Francisco Larghi","_149":"Enrique Accossato","_150":"Bombero Atilio Ronco","_151":"Int Carlos Alvarez","_152":"25 de Mayo","_153":"Gerónimo L. de Cabrera","_154":"Carcano","_155":"Carlos Pellegrini","_156":"Doctor Diego Montoya","_157":"Hipólito Irigoyen","_158":"Italia","_159":"Lugones","_160":"Mendoza","_161":"Pasaje Sucre","_162":"Urquiza","_163":"Antonio H. Palmero","_164":"Pasaje Cerro Champaquí","_165":"La Pampa","_166":"Juan Roasenda","_167":"Gobernador Paez Molina","_168":"Gobernador Arturo Zanicheli","_169":"Gobernador Brigadier San Martín","_170":"Tacuarí","_171":"Marcelino Bustos","_172":"Felix Bonangelino","_173":"Doctor Nelo L. Sartori","_174":"Manuel Chaves","_175":"Héctor J. Campora","_176":"Ismael Vera","_177":"Escritor Artemio Aran","_178":"Doctor Héctor Rujinsky","_179":"Doctor Julio Hernandez","_180":"Doctor Fernando Margiotti","_181":"Ronaldo Gervasoni","_182":"Tomas Salamanca","_183":"Emilio Almada","_184":"Doctora Alicia Moreu de Justo","_185":"Industrial Carlos Sturm","_186":"Martin Young","_187":"Ponte Luis Sergio","_188":"Tini Florencio","_189":"Carrara Hiriberto","_190":"Mosello Aldo José","_191":"Nieto Eugenio","_192":"Lerida Nieto de Aloe","_193":"Dupraz Sergio","_194":"Sacavino Nelson","_195":"Palavecino Ricardo","_196":"Olivero Ermi","_197":"Rujinsky José","_198":"Agustin Tosco","_199":"Enrique Vidal","_200":"Doctor Julio Hernández Hijo","_201":"Filippi Italo"}