{"1":[24,36,70,101],"2":[2,15,26,85],"9":[71],"_0":"Carlos Vechietti","C":[0,5,11,29,37,41,43,48,52,87,88,93,100,101,103,104,105],"V":[0,17,59,96,102],"_1":"Remedios de Escalada","R":[1,3,7,16,19,48,49,53,77,90,94,101],"d":[1,2,5,15,17,20,24,25,26,74,85,93,98,100,103],"E":[1,18,86,101,105],"_2":"2 de Abril","A":[2,12,13,16,17,19,24,25,27,31,33,38,40,41,47,50,51,64,67,72,73,74,75,76,91,93,106],"_3":"Nelida Rodriguez","N":[3,9,23,45,64,106],"_4":"Salta","S":[4,6,8,22,42,44,56,67,74,76,81,82],"_5":"Madre Teresa de Calculata","M":[5,9,10,15,18,25,36,38,58,60,63,65,66,74,82,84,85,93,100,103],"T":[5,14,30,39,40,62,86],"_6":"Simon Bolivar","B":[6,13,52,53,58,73,75,77,95,104],"_7":"Doctor Riat","D":[7,23,33,36,38,62,65,70,71,78,82],"_8":"San Lorenzo","L":[8,20,21,27,34,35,46,47,69,79,89,91,94,95,99],"_9":"Nicolás Magdaleno","_10":"Maipú","_11":"Caseros","_12":"Antonio Galizzi","G":[12,20,23,29,30,54,55,63,65,74,96,104,105],"_13":"Buenos Aires","_14":"Tucumán","_15":"29 de Mayo","_16":"Julio A Roca","J":[16,23,25,26,31,33,44,56,61,71,74,75,83,84,97,98,102],"_17":"V. A. de Valieri","_18":"Melitona Enrique","_19":"Adelina Roig Flores","F":[19,67,81,88,95],"_20":"General Gregorio de Las Heras","H":[20,28,59,94],"_21":"Libertad","_22":"Saenzpena","_23":"Natalia J. De Gutierez","_24":"17 de Agosto","_25":"Alicia Moreau de Justo","_26":"20 de Junio","_27":"Luis Aguilar","_28":"Hipólito Yrigoyen","Y":[28],"_29":"Pasaje Capitán Giachino","P":[29,31,40,52,54,57,61,84,89,99,102],"_30":"Timoteo Garces","_31":"Pasaje Juan Almiron","_32":"Wilde","W":[32],"_33":"Doctor José Alvarez","_34":"Ángel Lagatta","Á":[34],"_35":"Los Lapachos","_36":"1 De Mayo","_37":"Córdoba","_38":"Marcelo De Alvear","_39":"Tacuari","_40":"Pasaje Agustín Tosco","_41":"Adolfo Codutti","_42":"Suipacha","_43":"Chacabuco","_44":"Jose Suligoy","_45":"Neuquén","_46":"Laprida","_47":"Los Acheros","_48":"Rosa Chara","_49":"Reconquista","_50":"Antártida Argentina","_51":"Ayohuma","_52":"Pasaje Benito Colaneri","_53":"Berbardino Rivadavia","_54":"Pasaje Oscar Garses","O":[54,70,80,82],"_55":"Guemes","_56":"San Juan","_57":"Pueyrredon","_58":"Bartolomé Mitre","_59":"Hermanos Velazques","_60":"Misiones","_61":"Primera Junta","_62":"Dante Tardelli","_63":"Martín Goaper","_64":"Nicolás Avellanega","_65":"Martín Miguel De Güemes","_66":"Mariano Moreno","_67":"Soldado Felix Aguirre","_68":"Uruguay","U":[68,98],"_69":"Los Quebrachos","Q":[69],"_70":"12 De Octubre","_71":"9 De Julio","_72":"Arneodo","_73":"Avenida Belgrano","_74":"Avenida General José de San Martín","_75":"Avenida Juan B. Alberdi","_76":"Avenida Sarmiento","_77":"Bernardino Rivadavia","_78":"Donovan","_79":"Lamadrid","_80":"Obligado","_81":"Santa Fe","_82":"Santa Maria De Oro","_83":"Juncal","_84":"Pasaje José Martín","_85":"25 de Mayo","_86":"Teodolinda Ermacora","_87":"Corrientes","_88":"Calle Fernández","_89":"Los Pozos","_90":"Ricardo Rojas","_91":"Angel Lagatta","_92":"Imaginario","I":[92],"_93":"Carlos María de Alvea","_94":"Raúl L. Handera","_95":"Fray Luis Beltrán","_96":"General Vedia","_97":"Junin","_98":"Justo José de Urquiza","_99":"La Plata","_100":"Zulema C de Morales","Z":[100],"_101":"Calle EX RN 16","_102":"Pasaje Juan José Valle","_103":"Combatientes de Malvinas","_104":"Carlos B. Gomez","_105":"Ernesto Che Guevara","_106":"Anicibio Nistal"}