{"1":[129],"2":[131],"6":[214],"7":[201],"_0":"Carlos Calvo","C":[0,5,11,18,19,21,34,44,63,88,93,94,96,104,111,133,135,137,138,139,144,145,152,164,166,175,184,187,191,196,197,207,212,213,214,218],"_1":"Plus Ultra","P":[1,3,29,40,47,49,54,55,57,60,65,70,87,91,97,101,103,107,113,122,127,128,135,149,165,170,179,183,186,191,193,196,204,208,209,211,212,217,219],"U":[1,76,77],"_2":"Diego de Villarroel","D":[2,21,32,36,64,73,75,78,84,92,93,97,103,105,106,112,125,136,146,150,159,162,189,193,197,206],"d":[2,3,13,26,41,66,73,74,107,116,127,128,129,131,134,135,166,185,186,191,192,195,205,207,208,211,213,218],"V":[2,16,27,29,48,70,97,105,106,116,136,139,181,206,216],"_3":"Río de la Plata","R":[3,7,12,22,34,53,66,71,78,79,81,87,104,119,120,123,124,125,148,166,179,182],"l":[3,73,144,166,191,207,218],"_4":"Gervasio Mendez","G":[4,9,15,31,38,41,48,49,50,53,55,73,74,80,99,105,122,123,132,137,138,140,141,169,180,182,185,190,194,216],"M":[4,15,16,20,26,28,35,38,39,42,44,50,52,66,69,74,76,80,83,90,98,104,107,127,138,140,143,149,153,157,169,186,196,198,208,210,211],"_5":"Cataluña","_6":"Hilario Ascasubi","H":[6,25,26,68,163,167,187,213],"A":[6,13,19,21,32,43,51,64,67,79,88,91,93,100,106,109,114,124,126,131,134,138,142,147,154,156,159,168,171,174,188,190,192,197,203,206],"_7":"Belisario Roldán","B":[7,19,46,61,67,68,80,85,86,90,96,98,111,153,165,189,190,191,202,218],"_8":"Éxodo Jujeño","É":[8],"J":[8,10,14,27,30,37,48,52,58,61,67,82,94,96,115,118,158,159,163,178,179,194,207,215],"_9":"Timoteo Gordillo","T":[9,14,17,35,44,62,89,102,195,217],"_10":"Juan Stefani","S":[10,22,30,36,39,42,44,58,66,82,84,92,95,97,98,100,108,128,143,148,150,160,176,178,220],"_11":"Evaristo Carriego","E":[11,23,30,43,45,56,66,72,76,86,92,95,106,113,132,145,170,172,177,180,192,194,199],"_12":"Ricardo Rojas","_13":"Félix de Azara","F":[13,24,32,33,34,35,40,41,44,55,75,89,119,121,125,128,148,161,176,182,205],"_14":"José Ignacio Thames","I":[14,111,132,144,193],"_15":"General Manuel Oribe","O":[15,35,63,120,121,129,130,155,169,173,175,178,212],"_16":"Mariano Vedia y Mitre","y":[16,70],"_17":"Tablada","_18":"Canadá","_19":"Avenida Bernardo Caveri","_20":"Montgolfier","_21":"Doctor Alexis Carrel","_22":"Santa Rosa","_23":"España","_24":"Filipinas","_25":"Hernandarias","_26":"Hernando de Magallanes","_27":"Juan Vucetich","_28":"Manuel Maza","_29":"Vicente Yañez Pinzón","Y":[29],"_30":"Juan Sebastián Elcano","_31":"General Gregorio Lemos","L":[31,33,39,59,61,70,85,94,99,108,109,116,126,134,135,136,143,155,156,168,185,192,195,199,200,205,209,217],"_32":"Doctor Alexander Fleming","_33":"Federico Lacroze","_34":"Comandante Ramón Franco","_35":"Teniente Manuel Félix Origone","_36":"Santos Dumont","_37":"Jorge Newbery","N":[37,61,139,151,184,197,210],"_38":"Martín Gil","_39":"Sor María Luján Sierra","_40":"Francisco Pizarro","_41":"Francisco de Goya","_42":"Marcos Sastre","_43":"Albert Einstein","_44":"Soldado Conscripto Fernando Marcelo Toledo","_45":"Ecuador","_46":"Barker","_47":"Portugal","_48":"Joaquín Víctor González","_49":"Giácomo Puccini","_50":"Manuel Gálvez","_51":"Andinos","_52":"Juan Milton","_53":"Ricardo Gutiérrez","_54":"Pitágoras","_55":"General Francisco Pinto","_56":"Esteban Echeverría","_57":"Perú","_58":"San Justo","_59":"Líbano","_60":"Paraguay","_61":"Lord Jorge Noel Byron","_62":"Tapiales","_63":"Clemente Onelli","_64":"Alejandro Dumas","_65":"Potosí","_66":"Remedios de Escalada de San Martín","_67":"Juan Bautista Azopardo","_68":"Hipólito Bouchard","_69":"Maipú","_70":"Vicente López y Planes","_71":"Rosario","_72":"Euskadi","_73":"Doctor Ginés de la Quintana","Q":[73,110,117,161],"_74":"General Martín de Gainza","_75":"Deán Funes","_76":"María Elena Uhart","_77":"Uruguay","_78":"República Dominicana","_79":"Roald Amundsen","_80":"General Manuel Belgrano","_81":"Roma","_82":"Jorge Stephenson","_83":"Mendoza","_84":"Don Segundo Sombra","_85":"Luis Beláustegui","_86":"Esteban Bongiovanni","_87":"Puente Roca","_88":"Arturo Capdevila","_89":"Teodoro Fels","_90":"Benjamin Matienzo","_91":"Astor Piazzolla","_92":"Enrique Santos Discepolo","_93":"Doctor Cosme Argerich","_94":"Juan Crisóstomo Lafinur","_95":"San Emilio","_96":"Cura José Brochero","_97":"San Vicente De Paul","_98":"Boulogne Sur Mer","_99":"La Gazeta","_100":"Alfonsina Storni","_101":"Pericles","_102":"Triunvirato","_103":"Domingo Parodi","_104":"Mariscal Ramón Castilla","_105":"Vasco Da Gama","_106":"Eustoquio Antonio Díaz Vélez","_107":"Pedro de Mendoza","_108":"Solano López","_109":"Las Américas","_110":"Quilmes","_111":"Intendente Benito Corvalán","_112":"Defensa","_113":"Pedro Echagüe","_114":"Andalucía","_115":"Junin","_116":"Virgen de Luján","_117":"Quintana","_118":"Jacarandá","_119":"Robert Fulton","_120":"Rafael Obligado","_121":"Federico Ozanam","_122":"Gregorio Perdriel","_123":"Ricardo Güiraldes","_124":"República Argentina","_125":"Doctor René Favaloro","_126":"La Amistad","_127":"Manuel de Pinazo","_128":"Francisco de Paula Santander","_129":"17 de Octubre","_130":"Olmedo","_131":"2 de Abril","_132":"Intendente Emilio Gnecco","_133":"Chuquisaca","_134":"Avenida del Libertador","_135":"Ciudad de La Paz","_136":"Leonardo Da Vinci","_137":"George Clemenceau","_138":"Abanderado Cleto Mariano Grandoli","_139":"Coronel Niceto Vega","_140":"Guillermo Marconi","_141":"Galileo Galilei","_142":"Arroyo","_143":"La Santa María","_144":"Isabel la Católica","_145":"El Ceibo","_146":"Demóstenes","_147":"Albatros","_148":"Sargento Florencio Romero","_149":"Periodista Manuel Álvarez Pendas","Á":[149,196,204],"_150":"Dámaso Sánchez","_151":"Nogoyá","_152":"Cristóbal Colón","_153":"Bartolomé Murillo","_154":"Acoyte","_155":"Los Olmos","_156":"Los Aromos","_157":"Moctezuma","_158":"Jacobo Watt","W":[158],"_159":"Doctor Arturo Jauretche","_160":"Sófocles","_161":"Facundo Quiroga","_162":"Demostenes","_163":"José Hernández","_164":"Corrientes","_165":"Pedro Benoit","_166":"Camino de la Ribera","_167":"Homero","_168":"Abraham Lincoln","_169":"General Manuel Olazabal","_170":"Pedro Echagûe","_171":"Arribeños","_172":"Extremadura","_173":"Onas","_174":"Atalaya","_175":"Calixto Oyuela","_176":"Florencio Sánchez","_177":"Ensenada","_178":"Jorge S. Ohm","_179":"Roberto J. Payró","_180":"El Greco","_181":"Virrey Vertiz","_182":"Federico Guillermo Rauch","_183":"Plutarco","_184":"Ceferino Namuncurá","_185":"Gregorio de Laferrere","_186":"Puente de Marquez","_187":"Hernán Cortés","_188":"Aeronáutica Argentina","_189":"Don Bosco","_190":"Gustavo Adolfo Becquer","_191":"Pedro Calderón de la Barca","_192":"Ejército de Los Andes","_193":"Doctor Ignacio Pirovano","_194":"José Goncalves Eiras","_195":"Luis de Tejeda","_196":"Capitán Manuel Álvarez Prado","_197":"Avenida Doctor Néstor Carlos Kirchner","K":[197],"_198":"Magdalena","_199":"Enrique Larreta","_200":"Lamadrid","_201":"7 bis","b":[201],"_202":"Becquer","_203":"Azteca","_204":"Álvarez Prado","_205":"Fray Luis de León","_206":"Diagonal Alejandro Volta","_207":"Juan de la Cierva","_208":"Puente de Márquez","_209":"La Pinta","_210":"Nini Marshall","_211":"Mayor del Pino","_212":"Pasaje Clemente Onelli","_213":"Hugo del Carril","_214":"Calle 6","_215":"Junín","_216":"Valentín Gómez","_217":"Pasaje La Tosquera","_218":"Calderon de la Barca","_219":"Parodi","_220":"Santander"}