{"_0":"Faustino","f":[0,9,20,31,43,49,58,66,94],"_1":"Olga","o":[1,56,112],"_2":"Camilo","c":[2,17,18,34,116],"_3":"Hugo","h":[3,36,38,117,118,122],"_4":"Noemí","n":[4,47,107,109,110,111],"_5":"Bautista","b":[5,22,27,33],"_6":"Elisa","e":[6,7,16,23,24,29,42,44,53,54,67,92,121],"_7":"Enrique","_8":"Daniela","d":[8,13,15,40,93,95,108],"_9":"Félix","_10":"Ángel","á":[10,35],"_11":"Arturo","a":[11,14,19,26,30,32,52,80,127],"_12":"Mario","m":[12,28,45,46,51,64,75,79,83,91,125],"_13":"Rotonda del Tanque","r":[13,59,60,63,82,87,88,99],"t":[13,62],"_14":"Avenida Argentina","_15":"Domingo","_16":"Elena","_17":"Carmen","_18":"Cecilia","_19":"Adolfo","_20":"Fabián","_21":"Victoria","v":[21,61,86,96],"_22":"Braulio","_23":"Eva","_24":"Elina","_25":"Julio","j":[25,37,50,55,68,70,76,104,123,124],"_26":"Adriana","_27":"Brigida","_28":"General San Martín","g":[28,48,72,84,100,106,126],"s":[28,73,74,114],"_29":"Egidio","_30":"Armando","_31":"Felipe","_32":"Alicia","_33":"Bruno","_34":"Carlos","_35":"Ángela","_36":"Hilario","_37":"Juan","_38":"Héctor","_39":"Pascual","p":[39,41,77,78,81,97,113],"_40":"Daniel","_41":"Pierina","_42":"Evelina","_43":"Franca","_44":"Emma","_45":"Mirta","_46":"Marta","_47":"Narciso","_48":"Gertrudis","_49":"Francisca","_50":"José","_51":"Mariana","_52":"Avenida Abel","_53":"Eugenia","_54":"Emilio","_55":"Josefina","_56":"Osvaldo","_57":"Leticia","l":[57,69,71,89,98,103,105,116],"_58":"Florencia","_59":"Rita","_60":"Rosa","_61":"Víctor","_62":"Teresa","_63":"Rosana","_64":"Mariano","_65":"Inés","i":[65,90,101,102,119],"_66":"Florencio","_67":"Elsa","_68":"Jorge","_69":"Luciano","_70":"Jacinto","_71":"Luisa","_72":"Gabriel","_73":"Silvia","_74":"Sara","_75":"Margarita","_76":"Justo","_77":"Pedro","_78":"Praxedes","_79":"María","_80":"Analía","_81":"Pablo","_82":"Raquel","_83":"Marcos","_84":"Gregorio","_85":"Yolanda","y":[85],"_86":"Virginia","_87":"Roberto","_88":"Rodolfo","_89":"Leandro","_90":"Isidoro","_91":"Miguel","_92":"Evaristo","_93":"Dorothea","_94":"Francisco","_95":"Damián","_96":"Valentina","_97":"Paula","_98":"Luis","_99":"Ricardo","_100":"Guillermo","_101":"Ignacio","_102":"Irene","_103":"Lucio","_104":"Joaquín","_105":"Liliana","_106":"Graciela","_107":"Natalia","_108":"Diego","_109":"Natividad","_110":"Nora","_111":"Néstor","_112":"Ofelia","_113":"Patricia","_114":"Susana","_115":"Walter","w":[115],"_116":"Calle Lia","_117":"Hilda","_118":"Hipólito","_119":"Isabel","_120":"Óscar","ó":[120],"_121":"Estela","_122":"Higinio","_123":"Julián","_124":"Justa","_125":"Martín","_126":"Genaro","_127":"Aldo"}