{"2":[2],"7":[45],"_0":"General Paz","g":[0,6,48,53,55],"p":[0,1,4,10,21,28,33,50,54,55],"_1":"Pasaje Lugones","l":[1,4,26,35,39,44,52],"_2":"Bulevar 25 de Mayo","b":[2,11,14,16,24,31,33,35,39,46],"d":[2,9,30,33,36,44,51,55],"m":[2,5,13,14,30,36],"_3":"Saavedra","s":[3,7,9,14,18,32,54],"_4":"López y Planes","y":[4,31,43],"_5":"Mendoza","_6":"Güemes","_7":"Vélez Sarsfield","v":[7,47,53,55],"_8":"Rivadavia","r":[8,30,38,40,41,50,52,54],"_9":"Domingo Faustino Sarmiento","f":[9,18,31,35,42],"_10":"Pueyrredón","_11":"Belgrano","_12":"Urquiza","u":[12,23],"_13":"Mariano Moreno","_14":"Bulevar San Martín","_15":"Colón","c":[15,17,19,20,22,34,41,49],"_16":"Buenos Aires","a":[16,29,36,38,39,42,45,46,47,49],"_17":"Chile","_18":"Santa Fe","_19":"Cincuentenario","_20":"Córdoba","_21":"Paraguay","_22":"Centenario","_23":"Uruguay","_24":"Brasil","_25":"Italia","i":[25,28,47,48,50,53],"_26":"Esteban Larco","e":[26,27],"_27":"España","_28":"Pasaje Intendente Paviolo","_29":"Avellaneda","_30":"Juan Manuel de Rosas","j":[30,32,33,38,41,50],"_31":"French y Beruti","_32":"San Juan","_33":"Bulevar Juan Domingo Perón","_34":"Catamarca","_35":"Fray Luis Beltrán","_36":"Marcelo T. de Alvear","t":[36,37,44],"_37":"Tucumán","_38":"Julio Argentino Roca","_39":"Bulevar Leandro N. Alem","n":[39,40],"_40":"Rafael Nuñez","_41":"Ramón J. Cárcano","_42":"Alejandro Fleming","_43":"Hipólito Yrigoyen","h":[43],"_44":"Lisandro de la Torre","_45":"75 Aniversario","_46":"Almirante Brown","_47":"Intendente Andrés Vilosio","_48":"Intendente Gerlerlo","_49":"Camino al Cementerio","_50":"Intendente Presbítero José Rubiolo","_51":"Democracia","_52":"La Rioja","_53":"Intendente Ítalo Victorio Grangetto","í":[53],"_54":"Roque Sáenz Peña","_55":"Pasaje Doctor Víctor Guillermo Díaz"}