{"1":[[22,0],[24,0]],"2":[[23,0],[25,0],[26,0]],"9":[[28,0]],"_0":"Agustín Garzón","a":[[0,0],[5,9],[5,18],[5,27],[8,0],[10,0],[24,6],[29,0],[29,10],[34,0],[34,8],[40,14],[52,0],[52,16]],"g":[[0,8],[31,0],[47,0],[65,7]],"_1":"Santiago del Estero","s":[[1,0],[7,14],[12,0],[16,0],[17,0],[30,0],[31,8],[41,6],[45,0],[46,6],[54,0]],"d":[[1,9],[3,0],[4,0],[7,0],[14,13],[22,3],[23,3],[24,3],[25,3],[26,3],[28,2],[39,17],[58,0],[62,11]],"e":[[1,13],[37,0],[42,13],[48,0],[55,12]],"_2":"Isaías Koen","i":[[2,0],[9,0],[27,0],[36,0],[60,0]],"k":[[2,7]],"_3":"Deán Funes","f":[[3,5],[12,6],[19,0],[42,0],[43,7],[50,0]],"_4":"Doctor Lobo Castellanos","l":[[4,7],[17,4],[18,0],[18,9],[33,0],[39,0],[63,0]],"c":[[4,12],[15,0],[20,0],[32,0],[39,20],[44,0],[51,0],[57,0]],"_5":"Monseñor Aquilino Argüello Ardiles","m":[[5,0],[6,0],[6,8],[7,7],[21,0],[25,6],[31,12],[42,5],[49,0],[53,8],[55,5],[56,10],[60,6],[64,0],[65,0]],"_6":"Mariano Moreno","_7":"Doctor Miguel Sucaría","_8":"América","_9":"Ingeniero Ríos","r":[[9,10],[11,0],[33,3],[48,6],[52,8],[53,0],[61,8]],"_10":"Avellaneda","_11":"Reconquista","_12":"Santa Fe","_13":"Jorge Newbery","j":[[13,0],[22,6],[26,6],[28,5],[38,0],[40,0],[55,0],[61,0],[62,0],[62,6]],"n":[[13,6],[14,17],[16,10],[23,6]],"_14":"Pasaje Paseo del Niño","p":[[14,0],[14,7],[43,0]],"_15":"Constitución","_16":"Soberanía Nacional","_17":"San Lorenzo","_18":"Leopoldo Lugones","_19":"Falucho","_20":"Chaco","_21":"Maipú","_22":"10 de Junio","_23":"23 de Noviembre","_24":"17 de Agosto","_25":"25 de Mayo","_26":"20 de Junio","_27":"Independencia","_28":"9 de Julio","_29":"Antártida Argentina","_30":"Salta","_31":"General San Martín","_32":"Chacabuco","_33":"La Rioja","_34":"Avenida Argentina","_35":"Tucumán","t":[[35,0],[39,9]],"_36":"Italia","_37":"España","_38":"Jujuy","_39":"Ludovica Toccoli de Conti","_40":"Juan Bautista Alberdi","b":[[40,5],[47,8],[56,0],[58,7],[64,10]],"_41":"Vélez Sarsfield","v":[[41,0],[46,0]],"_42":"Fray Mamerto Esquiú","_43":"Pasaje Fátima","_44":"Colón","_45":"Sarmiento","_46":"Velez Sarsfield","_47":"General Belgrano","_48":"Entre Ríos","_49":"Misiones","_50":"Formosa","_51":"Corrientes","_52":"Avenida Rafaela Amenabar","_53":"Rogelio Martínez","_54":"Sarachaga","_55":"José Manuel Estrada","_56":"Bartolomé Mitre","_57":"Catamarca","_58":"Doctor Berrotarán","_59":"Hipólito Yrigoyen","h":[[59,0]],"y":[[59,9]],"_60":"Islas Malvinas","_61":"Jacinto Ríos","_62":"Justo José de Urquiza","u":[[62,14]],"_63":"Libertad","_64":"Marcelino Berrotarán","_65":"Martín Güemes","#prov_name":"Córdoba","#city_name":"Berrotarán"}