{"1":[[0,0],[1,0],[2,0],[3,0],[4,0],[5,0],[6,0],[7,0],[8,0],[9,0],[10,0],[11,0],[12,0],[13,0],[14,7],[15,0],[16,0],[16,6],[16,21],[17,0],[18,0],[19,0],[20,0],[21,0],[22,0],[23,9],[24,0],[25,7],[26,0],[27,0],[27,21],[28,0],[29,0],[30,0],[30,20],[31,0],[32,0],[33,0],[34,0],[35,0],[36,0],[37,0],[38,0],[39,7],[40,0],[41,0],[42,0],[43,7],[44,0],[45,9],[46,8],[47,7],[48,0],[49,7],[50,8],[51,0]],"2":[[27,6],[30,6],[32,6]],"9":[[48,6]],"_0":"116 - Almirante Brown","-":[[0,4],[1,4],[2,4],[3,4],[4,4],[5,4],[6,4],[7,4],[8,4],[9,4],[10,4],[11,4],[12,4],[13,4],[14,11],[15,4],[16,4],[17,4],[18,4],[19,4],[20,4],[21,4],[22,4],[24,4],[25,11],[26,4],[27,4],[28,4],[29,4],[30,4],[31,4],[32,4],[33,4],[34,4],[35,4],[36,4],[37,4],[38,4],[39,11],[40,4],[41,4],[42,4],[44,4],[45,13],[46,12],[47,11],[48,4],[49,11],[50,12],[51,4]],"a":[[0,6],[2,6],[16,11],[24,6],[30,11],[46,0],[50,0]],"b":[[0,16],[2,26],[3,6],[39,18],[45,15],[46,29]],"_1":"112 - Vicente López","v":[[1,6],[29,11]],"l":[[1,14],[9,19],[12,6],[14,21],[21,6],[34,14]],"_2":"116 - Almirante Guillermo Brown","g":[[2,16],[5,6],[9,6],[34,6],[45,25]],"_3":"120 - Balcarce","_4":"107 - Cabildo","c":[[4,6],[8,6],[13,6],[14,13],[15,17],[24,14],[33,6],[35,6],[37,15],[41,15],[44,6],[47,13]],"_5":"122 - General Roca","r":[[5,14],[28,6],[45,48],[46,21]],"_6":"117 - Pichincha","p":[[6,6],[12,12],[14,0],[15,6],[25,0],[29,20],[29,34],[31,14],[38,6],[39,0],[43,0],[47,0],[47,25],[49,0],[49,24],[50,18]],"_7":"115 - Maestro Dasso","m":[[7,6],[10,6],[11,6],[18,6],[25,13],[31,6],[32,12],[34,29],[36,6],[40,6],[42,6],[45,38]],"d":[[7,14],[16,8],[16,18],[23,0],[27,9],[27,18],[29,6],[29,31],[30,8],[30,17],[31,10],[32,9],[45,0],[45,45],[46,14],[47,22],[48,8],[49,21]],"_8":"112 - Conesa","_9":"123 - General Juan Lavalle","j":[[9,14],[27,12],[39,13],[45,33],[48,11]],"_10":"119 - Martín Ocampo","o":[[10,13]],"_11":"118 - Maipú","_12":"105 - Lynch Pueyrredón","_13":"124 - Colón","_14":"Pasaje 115 - Capitán López","_15":"111 - Presbítero Carballo","_16":"109 - 1 de Agosto de 1806","_17":"134 - Treinta y Tres","t":[[17,6],[17,16]],"y":[[17,14]],"_18":"132 - Montevideo","_19":"119 - España","e":[[19,6],[50,14]],"_20":"123 - Nápoles","n":[[20,6]],"_21":"126 - Lafayette","_22":"136 - Sarandí","s":[[22,6],[34,25],[37,6],[41,6],[51,6]],"_23":"Diagonal 122","_24":"117 - Avenida Colón","_25":"Pasaje 130 - Monteagudo","_26":"111 - Urquiza","u":[[26,6]],"_27":"103 - 26 de Julio de 1890","_28":"142 - Reconquista","_29":"144 - Doña Victoria Pueyrredón de Pueyrredón","_30":"140 - 2 de Abril de 1982","_31":"148 - Mar del Plata","_32":"113 - 25 de Mayo","_33":"146 - Campichuelo","_34":"115 - General Libertador San Martín","_35":"130 - Cuba","_36":"138 - Maipú","_37":"121 - Sargento Cabral","_38":"135 - Paraná","_39":"Pasaje 148 - José Betinotti","_40":"118 - Martín Fierro","f":[[40,13]],"_41":"117 - Sargento Cabral","_42":"150 - Mónaco","_43":"Pasaje 117","_44":"134 - Chacabuco","_45":"Diagonal 190 - Brigadier General Juan Manuel de Rosas","_46":"Avenida 101 - Doctor Ricardo Balbín","_47":"Pasaje 124 - Caseríos de Perdriel","_48":"116 - 9 de Julio","_49":"Pasaje 113 - Husáres de Pueyrredón","h":[[49,13]],"_50":"Avenida 125 - Eva Perón","_51":"114 - Suipacha"}