{"3":[[31,0]],"_0":"Cosquín","c":[[0,0],[1,13],[2,6],[3,5],[4,3],[5,19],[6,15],[8,0],[10,0],[12,0],[14,0],[15,0],[15,7],[16,8],[18,3],[22,0],[23,6],[25,0],[26,0],[28,6],[30,19],[33,0],[34,0],[35,0],[38,0]],"_1":"Francisco de Céspedes","f":[[1,0],[5,0],[17,0]],"d":[[1,10],[5,10],[11,9],[13,5],[30,15],[34,5]],"_2":"Alejo Castex","a":[[2,0],[6,7],[8,9],[11,16],[19,0],[27,5],[36,0]],"_3":"Juan Casacuberta","j":[[3,0],[16,0],[23,0],[27,0],[29,0]],"_4":"B. Carbajal","b":[[4,0]],"_5":"Francisco de Paula Castañeda","p":[[5,13],[7,4],[13,0],[28,0],[37,0],[37,14]],"_6":"Manuel Antonio Castro","m":[[6,0],[12,8],[21,3],[29,5],[30,9]],"_7":"Los Patos","l":[[7,0],[11,12],[13,8],[13,12],[18,0]],"_8":"Clemente Ader","_9":"Urién","u":[[9,0]],"_10":"Cóndor","_11":"Ejército de los Andes","e":[[11,0],[21,0],[34,9]],"_12":"Coronel Manuel Rico","r":[[12,15],[32,0]],"_13":"Paso de los Libres","_14":"Crucero","_15":"Carlos Cassafousth","_16":"Jacinto Cueto","_17":"Fragata Sarmiento","s":[[17,8],[30,0],[37,11]],"_18":"La Cadera","_19":"Aguapey","_20":"Girardot","g":[[20,0],[27,13],[32,3]],"_21":"El Maestro","_22":"Camilo Torres","t":[[22,7],[24,0]],"_23":"Jorge Cardassy","_24":"Tenti","_25":"Copahue","_26":"Concordia","_27":"Juan Antonio Gelly","_28":"Pablo Ceretti","_29":"Juan Murazan","_30":"Salvador María del Carril","_31":"33 Orientales","o":[[31,3]],"_32":"R. Gibson","_33":"Corrales","_34":"Cruz del Eje","_35":"Coronda","_36":"Aroma","_37":"Pollcarpia S. Pola","_38":"Cevallos","#prov_name":"Buenos Aires","#city_name":"Veinte de Junio"}