{"1":[[25,8]],"2":[[4,0]],"9":[[13,8]],"_0":"Ingeniero Nicolás Salvatori","i":[[0,0]],"n":[[0,10],[34,0]],"s":[[0,18],[3,16],[9,9],[12,0],[17,0],[23,0],[33,0]],"_1":"Corrientes","c":[[1,0],[17,9],[27,0],[37,0],[38,9],[39,0],[41,0]],"_2":"Ezequiel Ramos Mexía","e":[[2,0],[27,10],[35,0],[36,8]],"r":[[2,9],[5,0],[29,0],[35,6]],"m":[[2,15],[3,8],[6,0],[11,11],[12,4],[19,0],[30,8],[30,16],[38,0]],"_3":"Avenida Maestro Sosa","a":[[3,0],[4,6],[8,11],[13,0],[14,9],[15,0],[16,0],[20,0],[20,8],[22,14],[25,0],[28,0],[29,6],[30,0],[31,7],[32,0],[36,0],[37,5],[18,9],[21,11]],"_4":"27 de Abril","d":[[4,3],[13,10],[24,5],[25,11],[25,14],[36,19],[36,23],[38,6],[40,0]],"_5":"Río Limay","l":[[5,4],[7,7],[8,7],[14,6],[21,7],[24,8]],"_6":"Mendoza","_7":"Pasaje Los Olmos","p":[[7,0],[8,0],[9,0],[11,0],[21,0],[24,0],[26,0],[28,8],[28,17],[32,8]],"o":[[7,11]],"_8":"Pasaje Los Aromos","_9":"Patricio Sánchez","_10":"Huinganco","h":[[10,0]],"_11":"Padre José María Brentana","j":[[11,6],[13,13],[22,0]],"b":[[11,17],[22,5],[26,7],[31,0]],"_12":"San Martín","_13":"Avenida 9 de Julio","_14":"Villa La Angostura","v":[[14,0]],"_15":"Andacollo","_16":"Amancay","_17":"Sargento Cabral","_18":"Gregorio Álvarez","g":[[18,0]],"_19":"Moquehue","_20":"Avenida Aguaribay","_21":"Pasaje Los Álamos","_22":"Juan Bautista Alberdi","_23":"Sarmiento","_24":"Paso de las Toscas","t":[[24,12]],"_25":"Avenida 12 de Diciembre","_26":"Pasaje Blanco","_27":"Colectora Este","_28":"Avenida Primeros Pobladores","_29":"Ramón Arias","_30":"Avenida Mariano Moreno","_31":"Buenos Aires","_32":"Avenida Prim","_33":"Santa Fe","f":[[33,6],[41,7]],"_34":"Neuquén","_35":"Entre Ríos","_36":"Avenida Expedición del Desierto","_37":"Cabo Alarcón","_38":"María de Churrarín","_39":"Costanera","_40":"Domuyo","_41":"Carmen Funes","#prov_name":"Neuquén","#city_name":"Picún Leufú"}