{"1":[[0,0],[32,0],[45,7]],"2":[[2,0],[17,0],[24,0]],"9":[[26,0]],"_0":"1 de Mayo","d":[[0,2],[1,8],[2,3],[6,8],[14,7],[17,3],[24,3],[26,2],[29,16],[31,12],[32,3],[41,0],[45,10],[46,9],[47,8],[49,8]],"m":[[0,5],[3,0],[8,0],[17,6],[28,0],[28,8],[31,5],[42,9]],"_1":"Avenida del Libertador","a":[[1,0],[5,0],[6,0],[6,12],[11,0],[16,0],[16,8],[18,0],[21,0],[27,0],[34,0],[35,0],[36,0],[37,0],[45,13],[47,0]],"l":[[1,12],[15,8],[25,8],[27,8],[40,11],[44,0],[44,5],[47,12]],"_2":"20 de Junio","j":[[2,6],[4,0],[10,0],[23,0],[26,5],[29,11],[30,0],[31,0]],"_3":"Merardo Gutierrez","g":[[3,8],[5,14],[12,0],[33,0],[33,8],[37,8],[42,0]],"_4":"Jujuy","_5":"Avenida Pedro Graf","p":[[5,8],[7,4],[12,8],[25,0],[29,0],[29,24],[38,6],[45,0]],"_6":"Avenida del Agricultor","_7":"Eva Perón","e":[[7,0],[46,12],[51,0]],"_8":"Malvinas","_9":"Humberto Chazarreta","h":[[9,0],[30,5],[43,0]],"c":[[9,9],[10,6],[14,11],[39,0],[40,0],[48,0],[49,0]],"_10":"Jorge Corradi","_11":"Avenida Belgrano","b":[[11,8],[13,8],[19,8],[20,7],[38,0]],"_12":"General Paz","_13":"Ricardo Balbin","r":[[13,0],[18,8],[20,0],[22,0],[31,15],[46,0]],"_14":"Victor del Campo","v":[[14,0],[21,8],[48,9]],"_15":"Ignacio López","i":[[15,0],[19,0],[36,7]],"_16":"Alfredo Amaya","_17":"25 de Mayo","_18":"Avenida Rivadavia","_19":"Ignacio Barranza","_20":"Regino Barros","_21":"Antonio Vitolo","_22":"Raimundo Nirenpeger","n":[[22,9],[39,8],[49,11]],"_23":"Juan Sterzer","s":[[23,5],[24,6],[37,14]],"_24":"20 de Septiembre","_25":"Pelagio Luna","_26":"9 de Julio","_27":"Avenida Lavalle","_28":"Mariano Moreno","_29":"Presidente Juan Domingo Perón","_30":"Jose Hernandez","_31":"Juan Manuel de Rosas","_32":"17 de Octubre","o":[[32,6],[47,23]],"_33":"Gustavo Grenda","_34":"Achap","_35":"Anselmo Zoucca","z":[[35,8],[51,8]],"_36":"Arturo Illia","_37":"Avenida Gines Sanchez","_38":"Bruno Paez","_39":"Corazón Navarro","_40":"Cristoforo Larralde","_41":"Diogenes Taboada","t":[[41,9],[50,0]],"_42":"Geronimo Merello","_43":"Hipolito Yrigoyen","y":[[43,9]],"_44":"Luis Luna","_45":"Pasaje 17 de Agosto","_46":"Remedios de Escalada","_47":"Avenida del Libertador Oeste","_48":"Cristina Vargas","_49":"Corazón De Navarro","_50":"Tucumán","_51":"Eduardo Zaiser","#prov_name":"Chaco","#city_name":"Hermoso Campo"}