{"2":[[9,0]],"4":[[19,16]],"9":[[0,0]],"_0":"9 de Julio","d":[[0,2],[9,3],[26,9]],"j":[[0,5],[4,0],[31,7]],"_1":"Transito Ruiz","t":[[1,0],[32,5]],"r":[[1,9],[2,0],[8,0],[19,0],[32,0]],"_2":"Rivadavia","_3":"Lapdrida","l":[[3,0],[6,8],[7,4],[20,0],[22,0],[26,12],[28,0],[29,0]],"_4":"José Marmol","m":[[4,5],[9,6],[18,0],[21,4],[24,0],[24,8],[30,0],[31,0]],"_5":"Buenos Aires","b":[[5,0],[23,0]],"a":[[5,7],[10,8],[26,16],[30,9]],"_6":"Vicente López y Planes","v":[[6,0]],"y":[[6,14],[27,9]],"p":[[6,16],[13,0],[19,5],[25,0]],"_7":"San Luis","s":[[7,0],[16,0],[17,0],[21,0]],"_8":"Rosario","_9":"25 de Mayo","_10":"Nicolás Avellaneda","n":[[10,0]],"_11":"Hipólito Irigoyen","h":[[11,0],[27,0]],"i":[[11,9]],"_12":"Echeverría","e":[[12,0],[15,0],[26,0]],"_13":"Pringles","_14":"Urquiza","u":[[14,0]],"_15":"España","_16":"Sarmiento","_17":"Santa Fe","f":[[17,6]],"_18":"Mitre","_19":"Ruta Provincial 4","_20":"Loisa","_21":"San Martín","_22":"Lafinur","_23":"Belgrano","_24":"Mariano Moreno","_25":"Pueyrredon","_26":"Ejercito De Los Andes","_27":"Hipolito Yrigoyen","_28":"Laprida","_29":"Loaiza","_30":"Malvinas Argentinas","_31":"Marmol Jose","_32":"Ruiz Transito"}