{"2":[18],"_0":"Teniente General Juan Domingo Perón","t":[0,13,20],"g":[0],"j":[0],"d":[0,9,10,18],"p":[0,3,4,6,7,10],"_1":"Lavalle","l":[1,2,8,10],"_2":"Libertad","_3":"Rodríguez Peña","r":[3,4,11,26],"_4":"Avenida Presidente Roque Sáenz Peña","a":[4,8,16],"s":[4,19,23,25],"_5":"Esmeralda","e":[5],"_6":"Paraná","_7":"Carlos Pellegrini","c":[7,9,12,16],"_8":"Avenida Leandro N. Alem","n":[8],"_9":"Del Carmen","_10":"Pasaje Luis Dellepiane","_11":"Rodolfo Rivarola","_12":"Cerrito","_13":"Tucumán","_14":"Uruguay","u":[14],"_15":"Bartolomé Mitre","b":[15,21],"m":[15,18,22,24,25],"_16":"Avenida Corrientes","_17":"Viamonte","v":[17],"_18":"25 de Mayo","_19":"Suipacha","_20":"Talcahuano","_21":"Bouchard","_22":"Maipú","_23":"Sarmiento","_24":"Montevideo","_25":"San Martín","_26":"Reconquista"}